fev/__about__.py
fev/__init__.py
fev/adapters.py
fev/analysis.py
fev/benchmark.py
fev/constants.py
fev/metrics.py
fev/task.py
fev/utils.py
fev-0.7.0.dist-info/METADATA
fev-0.7.0.dist-info/WHEEL
fev-0.7.0.dist-info/licenses/LICENSE
fev-0.7.0.dist-info/licenses/NOTICE
fev-0.7.0.dist-info/RECORD
