Metadata-Version: 2.4
Name: fev
Version: 0.7.0
Summary: fev: Forecast evaluation library
Project-URL: Homepage, https://github.com/autogluon/fev
Project-URL: Issues, https://github.com/autogluon/fev/issues
Author-email: Oleksandr Shchur <shchuro@amazon.com>, Lorenzo Stella <stellalo@amazon.com>, Caner Turkmen <atturkm@amazon.com>, Abdul Fatir Ansari <ansarnd@amazon.com>
License: 
License-File: LICENSE
License-File: NOTICE
Classifier: License :: OSI Approved :: Apache Software License
Classifier: Operating System :: OS Independent
Classifier: Programming Language :: Python :: 3
Classifier: Topic :: Scientific/Engineering :: Artificial Intelligence
Requires-Python: >=3.10
Requires-Dist: datasets[s3]<4.0,>=2.15
Requires-Dist: numpy
Requires-Dist: pydantic~=2.0
Requires-Dist: scipy
Provides-Extra: test
Requires-Dist: aiobotocore==2.26.0; extra == 'test'
Requires-Dist: autogluon-timeseries>=1.1.1; extra == 'test'
Requires-Dist: boto3==1.41.5; extra == 'test'
Requires-Dist: botocore==1.41.5; extra == 'test'
Requires-Dist: jupyter; extra == 'test'
Requires-Dist: nbconvert; extra == 'test'
Requires-Dist: nbformat; extra == 'test'
Requires-Dist: pytest; extra == 'test'
Requires-Dist: ruff; extra == 'test'
